[
  { "id": "m1", "name": "Gà khô", "price": 10000, "category": "Đồ nhậu", "img": "img/ga_kho_1784555263538.png" },
  { "id": "m2", "name": "Bò khô", "price": 10000, "category": "Đồ nhậu", "img": "img/bo_kho_1784555277747.png" },
  { "id": "m3", "name": "Cơm gà", "price": 10000, "category": "Đồ nhậu", "img": "img/com_ga_1784555291315.png" },
  { "id": "m4", "name": "Lẩu thập cẩm", "price": 40000, "category": "Đồ nhậu", "img": "img/lau_1784555305730.png" },
  { "id": "m5", "name": "Lem chua", "price": 10000, "category": "Đồ nhậu", "img": "img/nem_chua_1784555317416.png" },
  { "id": "m6", "name": "Cánh gà chiên nước mắm", "price": 20000, "category": "Đồ nhậu", "img": "img/canh_ga_chien_1784555328189.png" },
  { "id": "m7", "name": "Đậu hũ chiên", "price": 10000, "category": "Đồ nhậu", "img": "img/dau_hu_chien_1784555339119.png" },
  { "id": "m8", "name": "Khoai tây chiên", "price": 10000, "category": "Đồ nhậu", "img": "img/khoai_tay_chien_1784555348743.png" },
  { "id": "m9", "name": "Chân gà bà tuyết", "price": 2000, "category": "Đồ nhậu", "img": "img/chan_ga_1784555360905.png" },
  { "id": "m10", "name": "Rượu", "price": 4500, "category": "Rượu bia", "img": "img/ruou_1784555370075.png" },
  { "id": "m11", "name": "Bia", "price": 4500, "category": "Rượu bia", "img": "img/bia_1784555381474.png" },
  { "id": "m12", "name": "Bia hơi", "price": 5000, "category": "Rượu bia", "img": "img/bia_1784555381474.png" },
  { "id": "m13", "name": "Bia hơi to", "price": 25000, "category": "Rượu bia", "img": "img/bia_1784555381474.png" },
  { "id": "m14", "name": "Rượu pha bò húc nhỏ", "price": 20000, "category": "Rượu bia", "img": "img/ruou_1784555370075.png" },
  { "id": "m15", "name": "Rượu pha bò húc vừa", "price": 30000, "category": "Rượu bia", "img": "img/ruou_1784555370075.png" },
  { "id": "m16", "name": "Rượu pha bò húc to", "price": 50000, "category": "Rượu bia", "img": "img/ruou_1784555370075.png" },
  { "id": "m17", "name": "Rượu đặc biệt", "price": 120000, "category": "Rượu bia", "img": "img/ruou_1784555370075.png" },
  { "id": "m18", "name": "Bò húc", "price": 4000, "category": "Nước ngọt", "img": "img/bo_huc_1784555390560.png" },
  { "id": "m19", "name": "Stinh", "price": 4000, "category": "Nước ngọt", "img": "img/sting_1784555408246.png" },
  { "id": "m20", "name": "Nước mía", "price": 5000, "category": "Nước ngọt", "img": "img/nuoc_mia_1784555420011.png" },
  { "id": "m21", "name": "Trà", "price": 5000, "category": "Nước ngọt", "img": "https://images.unsplash.com/photo-1544145945-f90425340c7e?w=500&q=80" },
  { "id": "m22", "name": "Trà sữa", "price": 6000, "category": "Nước ngọt", "img": "https://images.unsplash.com/photo-1558160074-4d7d8bdf4256?w=500&q=80" },
  { "id": "m23", "name": "Me đá", "price": 5000, "category": "Nước ngọt", "img": "https://images.unsplash.com/photo-1499638673689-79a0b5115d87?w=500&q=80" },
  { "id": "m24", "name": "Sâm dứa", "price": 5000, "category": "Nước ngọt", "img": "https://images.unsplash.com/photo-1513558161293-cdaf765ed2fd?w=500&q=80" },
  { "id": "m25", "name": "Trà đào", "price": 5000, "category": "Nước ngọt", "img": "https://images.unsplash.com/photo-1556679343-c7306c1976bc?w=500&q=80" },
  { "id": "m26", "name": "Cơm", "price": 1000, "category": "Gọi thêm", "img": "https://images.unsplash.com/photo-1536304929831-ee1ca9d44906?w=500&q=80" },
  { "id": "m27", "name": "Nước", "price": 0, "category": "Gọi thêm", "img": "https://images.unsplash.com/photo-1559839914-17aae19cb549?w=500&q=80" },
  { "id": "m28", "name": "Khăn ướt", "price": 5000, "category": "Gọi thêm", "img": "https://images.unsplash.com/photo-1584824388147-3bd4cda2402e?w=500&q=80" },
  { "id": "m29", "name": "Chân giò", "price": 30000, "category": "Đồ nhậu", "img": "https://images.unsplash.com/photo-1627308595229-7830b5c9660c?w=500&q=80" },
  { "id": "m30", "name": "Chân giò sốt cay", "price": 20000, "category": "Đồ nhậu", "img": "https://images.unsplash.com/photo-1562967914-608f82629710?w=500&q=80" }
]
